LICENSE
README.md
setup.cfg
setup.py
PyClassCharts.egg-info/PKG-INFO
PyClassCharts.egg-info/SOURCES.txt
PyClassCharts.egg-info/dependency_links.txt
PyClassCharts.egg-info/requires.txt
PyClassCharts.egg-info/top_level.txt
classcharts/__init__.py
classcharts/student.py
classcharts/utils.py