Metadata-Version: 2.1
Name: PyClassCharts
Version: 0.0.1
Summary: An unofficial package for interacting with the ClassCharts API
Home-page: https://github.com/itsnotrin/PyClassCharts
Author: Ryan Wiecz
Author-email: ryan@ryanwiecz.codes
Project-URL: Bug Tracker, https://github.com/itsnotrin/PyClassCharts/issues
Classifier: Programming Language :: Python :: 3
Classifier: License :: OSI Approved :: MIT License
Classifier: Operating System :: OS Independent
Requires-Python: >=3.7.0
License-File: LICENSE
